{
  "dataset_revision": "faeb762787bd10488a50c8b5be4a3b82e411949c",
  "task_name": "STS17",
  "mteb_version": "2.10.14",
  "scores": {
    "test": [
      {
        "pearson": 0.720931,
        "spearman": 0.721107,
        "cosine_pearson": 0.720931,
        "cosine_spearman": 0.721107,
        "manhattan_pearson": 0.727769,
        "manhattan_spearman": 0.726529,
        "euclidean_pearson": 0.727978,
        "euclidean_spearman": 0.726832,
        "main_score": 0.721107,
        "hf_subset": "ko-ko",
        "languages": [
          "kor-Hang"
        ]
      },
      {
        "pearson": 0.654501,
        "spearman": 0.67123,
        "cosine_pearson": 0.654501,
        "cosine_spearman": 0.671145,
        "manhattan_pearson": 0.663299,
        "manhattan_spearman": 0.673903,
        "euclidean_pearson": 0.662181,
        "euclidean_spearman": 0.669924,
        "main_score": 0.671145,
        "hf_subset": "ar-ar",
        "languages": [
          "ara-Arab"
        ]
      },
      {
        "pearson": 0.488135,
        "spearman": 0.484807,
        "cosine_pearson": 0.488135,
        "cosine_spearman": 0.484807,
        "manhattan_pearson": 0.473162,
        "manhattan_spearman": 0.469564,
        "euclidean_pearson": 0.481033,
        "euclidean_spearman": 0.473955,
        "main_score": 0.484807,
        "hf_subset": "en-ar",
        "languages": [
          "eng-Latn",
          "ara-Arab"
        ]
      },
      {
        "pearson": 0.614469,
        "spearman": 0.608523,
        "cosine_pearson": 0.614469,
        "cosine_spearman": 0.608523,
        "manhattan_pearson": 0.56921,
        "manhattan_spearman": 0.548623,
        "euclidean_pearson": 0.572529,
        "euclidean_spearman": 0.553366,
        "main_score": 0.608523,
        "hf_subset": "en-de",
        "languages": [
          "eng-Latn",
          "deu-Latn"
        ]
      },
      {
        "pearson": 0.835509,
        "spearman": 0.843995,
        "cosine_pearson": 0.835509,
        "cosine_spearman": 0.843995,
        "manhattan_pearson": 0.833701,
        "manhattan_spearman": 0.835391,
        "euclidean_pearson": 0.832587,
        "euclidean_spearman": 0.831508,
        "main_score": 0.843995,
        "hf_subset": "en-en",
        "languages": [
          "eng-Latn"
        ]
      },
      {
        "pearson": 0.126577,
        "spearman": 0.083697,
        "cosine_pearson": 0.126577,
        "cosine_spearman": 0.083697,
        "manhattan_pearson": 0.099849,
        "manhattan_spearman": 0.061184,
        "euclidean_pearson": 0.095753,
        "euclidean_spearman": 0.053155,
        "main_score": 0.083697,
        "hf_subset": "en-tr",
        "languages": [
          "eng-Latn",
          "tur-Latn"
        ]
      },
      {
        "pearson": 0.632441,
        "spearman": 0.639891,
        "cosine_pearson": 0.632441,
        "cosine_spearman": 0.639891,
        "manhattan_pearson": 0.622259,
        "manhattan_spearman": 0.628476,
        "euclidean_pearson": 0.624072,
        "euclidean_spearman": 0.629932,
        "main_score": 0.639891,
        "hf_subset": "es-en",
        "languages": [
          "spa-Latn",
          "eng-Latn"
        ]
      },
      {
        "pearson": 0.806286,
        "spearman": 0.797411,
        "cosine_pearson": 0.806286,
        "cosine_spearman": 0.797408,
        "manhattan_pearson": 0.822774,
        "manhattan_spearman": 0.793871,
        "euclidean_pearson": 0.819474,
        "euclidean_spearman": 0.790512,
        "main_score": 0.797408,
        "hf_subset": "es-es",
        "languages": [
          "spa-Latn"
        ]
      },
      {
        "pearson": 0.63844,
        "spearman": 0.641486,
        "cosine_pearson": 0.63844,
        "cosine_spearman": 0.641486,
        "manhattan_pearson": 0.614867,
        "manhattan_spearman": 0.602482,
        "euclidean_pearson": 0.626942,
        "euclidean_spearman": 0.614933,
        "main_score": 0.641486,
        "hf_subset": "fr-en",
        "languages": [
          "fra-Latn",
          "eng-Latn"
        ]
      },
      {
        "pearson": 0.639428,
        "spearman": 0.63329,
        "cosine_pearson": 0.639428,
        "cosine_spearman": 0.63329,
        "manhattan_pearson": 0.608743,
        "manhattan_spearman": 0.60137,
        "euclidean_pearson": 0.622201,
        "euclidean_spearman": 0.612442,
        "main_score": 0.63329,
        "hf_subset": "it-en",
        "languages": [
          "ita-Latn",
          "eng-Latn"
        ]
      },
      {
        "pearson": 0.389417,
        "spearman": 0.373698,
        "cosine_pearson": 0.389417,
        "cosine_spearman": 0.373698,
        "manhattan_pearson": 0.373734,
        "manhattan_spearman": 0.362159,
        "euclidean_pearson": 0.377309,
        "euclidean_spearman": 0.36393,
        "main_score": 0.373698,
        "hf_subset": "nl-en",
        "languages": [
          "nld-Latn",
          "eng-Latn"
        ]
      }
    ]
  },
  "evaluation_time": 2.285484552383423,
  "kg_co2_emissions": null,
  "date": null
}