{
  "dataset_revision": "815ca46b2622cec33ccafc3735d572c266efdb44",
  "task_name": "StackExchangeClusteringP2P.v2",
  "mteb_version": "2.10.14",
  "scores": {
    "test": [
      {
        "v_measures": {
          "Level 0": [
            0.315668,
            0.318188,
            0.320962,
            0.32072,
            0.314131,
            0.312943,
            0.319427,
            0.320245,
            0.322624,
            0.325683
          ]
        },
        "v_measure": 0.319059,
        "v_measure_std": 0.003721,
        "main_score": 0.319059,
        "hf_subset": "default",
        "languages": [
          "eng-Latn"
        ]
      }
    ]
  },
  "evaluation_time": 9.597145080566406,
  "kg_co2_emissions": null,
  "date": null
}