{
  "dataset_revision": "faeb762787bd10488a50c8b5be4a3b82e411949c",
  "task_name": "STS17",
  "mteb_version": "2.10.14",
  "scores": {
    "test": [
      {
        "pearson": 0.876786,
        "spearman": 0.883547,
        "cosine_pearson": 0.876786,
        "cosine_spearman": 0.883546,
        "manhattan_pearson": 0.873831,
        "manhattan_spearman": 0.882882,
        "euclidean_pearson": 0.874637,
        "euclidean_spearman": 0.883546,
        "main_score": 0.883546,
        "hf_subset": "ko-ko",
        "languages": [
          "kor-Hang"
        ]
      },
      {
        "pearson": 0.825506,
        "spearman": 0.833401,
        "cosine_pearson": 0.825506,
        "cosine_spearman": 0.833392,
        "manhattan_pearson": 0.815731,
        "manhattan_spearman": 0.832027,
        "euclidean_pearson": 0.818292,
        "euclidean_spearman": 0.833407,
        "main_score": 0.833392,
        "hf_subset": "ar-ar",
        "languages": [
          "ara-Arab"
        ]
      },
      {
        "pearson": 0.799335,
        "spearman": 0.797007,
        "cosine_pearson": 0.799335,
        "cosine_spearman": 0.797007,
        "manhattan_pearson": 0.806696,
        "manhattan_spearman": 0.797379,
        "euclidean_pearson": 0.809092,
        "euclidean_spearman": 0.797007,
        "main_score": 0.797007,
        "hf_subset": "en-ar",
        "languages": [
          "eng-Latn",
          "ara-Arab"
        ]
      },
      {
        "pearson": 0.880793,
        "spearman": 0.883769,
        "cosine_pearson": 0.880793,
        "cosine_spearman": 0.883769,
        "manhattan_pearson": 0.879377,
        "manhattan_spearman": 0.878967,
        "euclidean_pearson": 0.885087,
        "euclidean_spearman": 0.883769,
        "main_score": 0.883769,
        "hf_subset": "en-de",
        "languages": [
          "eng-Latn",
          "deu-Latn"
        ]
      },
      {
        "pearson": 0.934206,
        "spearman": 0.937081,
        "cosine_pearson": 0.934206,
        "cosine_spearman": 0.937081,
        "manhattan_pearson": 0.92945,
        "manhattan_spearman": 0.93438,
        "euclidean_pearson": 0.931398,
        "euclidean_spearman": 0.937081,
        "main_score": 0.937081,
        "hf_subset": "en-en",
        "languages": [
          "eng-Latn"
        ]
      },
      {
        "pearson": 0.795307,
        "spearman": 0.793775,
        "cosine_pearson": 0.795307,
        "cosine_spearman": 0.793775,
        "manhattan_pearson": 0.799782,
        "manhattan_spearman": 0.794445,
        "euclidean_pearson": 0.799212,
        "euclidean_spearman": 0.793775,
        "main_score": 0.793775,
        "hf_subset": "en-tr",
        "languages": [
          "eng-Latn",
          "tur-Latn"
        ]
      },
      {
        "pearson": 0.825787,
        "spearman": 0.837152,
        "cosine_pearson": 0.825787,
        "cosine_spearman": 0.837152,
        "manhattan_pearson": 0.839025,
        "manhattan_spearman": 0.836823,
        "euclidean_pearson": 0.84035,
        "euclidean_spearman": 0.837152,
        "main_score": 0.837152,
        "hf_subset": "es-en",
        "languages": [
          "spa-Latn",
          "eng-Latn"
        ]
      },
      {
        "pearson": 0.884629,
        "spearman": 0.881974,
        "cosine_pearson": 0.884629,
        "cosine_spearman": 0.881976,
        "manhattan_pearson": 0.894437,
        "manhattan_spearman": 0.88105,
        "euclidean_pearson": 0.894556,
        "euclidean_spearman": 0.881983,
        "main_score": 0.881976,
        "hf_subset": "es-es",
        "languages": [
          "spa-Latn"
        ]
      },
      {
        "pearson": 0.871627,
        "spearman": 0.867774,
        "cosine_pearson": 0.871627,
        "cosine_spearman": 0.867774,
        "manhattan_pearson": 0.873211,
        "manhattan_spearman": 0.863762,
        "euclidean_pearson": 0.875219,
        "euclidean_spearman": 0.867774,
        "main_score": 0.867774,
        "hf_subset": "fr-en",
        "languages": [
          "fra-Latn",
          "eng-Latn"
        ]
      },
      {
        "pearson": 0.89175,
        "spearman": 0.891613,
        "cosine_pearson": 0.89175,
        "cosine_spearman": 0.891613,
        "manhattan_pearson": 0.894289,
        "manhattan_spearman": 0.89104,
        "euclidean_pearson": 0.894046,
        "euclidean_spearman": 0.891613,
        "main_score": 0.891613,
        "hf_subset": "it-en",
        "languages": [
          "ita-Latn",
          "eng-Latn"
        ]
      },
      {
        "pearson": 0.882858,
        "spearman": 0.880224,
        "cosine_pearson": 0.882858,
        "cosine_spearman": 0.880224,
        "manhattan_pearson": 0.882876,
        "manhattan_spearman": 0.879401,
        "euclidean_pearson": 0.884028,
        "euclidean_spearman": 0.880224,
        "main_score": 0.880224,
        "hf_subset": "nl-en",
        "languages": [
          "nld-Latn",
          "eng-Latn"
        ]
      }
    ]
  },
  "evaluation_time": 9.324382305145264,
  "kg_co2_emissions": null,
  "date": null
}