{
  "dataset_revision": "815ca46b2622cec33ccafc3735d572c266efdb44",
  "task_name": "StackExchangeClusteringP2P.v2",
  "mteb_version": "2.10.14",
  "scores": {
    "test": [
      {
        "v_measures": {
          "Level 0": [
            0.357919,
            0.34811,
            0.345709,
            0.347687,
            0.340567,
            0.352003,
            0.349757,
            0.349746,
            0.345575,
            0.341028
          ]
        },
        "v_measure": 0.34781,
        "v_measure_std": 0.004851,
        "main_score": 0.34781,
        "hf_subset": "default",
        "languages": [
          "eng-Latn"
        ]
      }
    ]
  },
  "evaluation_time": 20.97080659866333,
  "kg_co2_emissions": null,
  "date": null
}