{
  "dataset_revision": "35191c8c0dca72d8ff3efcd72aa802307d469663",
  "task_name": "MedrxivClusteringS2S.v2",
  "mteb_version": "2.10.14",
  "scores": {
    "test": [
      {
        "v_measures": {
          "Level 0": [
            0.205286,
            0.207626,
            0.211998,
            0.209954,
            0.214998,
            0.199277,
            0.205633,
            0.200681,
            0.220071,
            0.196611
          ]
        },
        "v_measure": 0.207214,
        "v_measure_std": 0.006934,
        "main_score": 0.207214,
        "hf_subset": "default",
        "languages": [
          "eng-Latn"
        ]
      }
    ]
  },
  "evaluation_time": 6.177095174789429,
  "kg_co2_emissions": null,
  "date": null
}