{
  "dataset_revision": "3d86128a09e091d6018b6d26cad27f2739fc2db7",
  "task_name": "ImdbClassification",
  "mteb_version": "2.10.14",
  "scores": {
    "test": [
      {
        "scores_per_experiment": [
          {
            "accuracy": 0.49636,
            "f1": 0.49636,
            "f1_weighted": 0.49636,
            "precision": 0.49636,
            "precision_weighted": 0.49636,
            "recall": 0.49636,
            "recall_weighted": 0.49636,
            "ap": 0.498193,
            "ap_weighted": 0.498193
          },
          {
            "accuracy": 0.50348,
            "f1": 0.50267,
            "f1_weighted": 0.50267,
            "precision": 0.503503,
            "precision_weighted": 0.503503,
            "recall": 0.50348,
            "recall_weighted": 0.50348,
            "ap": 0.501751,
            "ap_weighted": 0.501751
          },
          {
            "accuracy": 0.4912,
            "f1": 0.49117,
            "f1_weighted": 0.49117,
            "precision": 0.491198,
            "precision_weighted": 0.491198,
            "recall": 0.4912,
            "recall_weighted": 0.4912,
            "ap": 0.495676,
            "ap_weighted": 0.495676
          },
          {
            "accuracy": 0.49936,
            "f1": 0.499271,
            "f1_weighted": 0.499271,
            "precision": 0.49936,
            "precision_weighted": 0.49936,
            "recall": 0.49936,
            "recall_weighted": 0.49936,
            "ap": 0.49968,
            "ap_weighted": 0.49968
          },
          {
            "accuracy": 0.5114,
            "f1": 0.511333,
            "f1_weighted": 0.511333,
            "precision": 0.511406,
            "precision_weighted": 0.511406,
            "recall": 0.5114,
            "recall_weighted": 0.5114,
            "ap": 0.505827,
            "ap_weighted": 0.505827
          },
          {
            "accuracy": 0.49776,
            "f1": 0.497361,
            "f1_weighted": 0.497361,
            "precision": 0.497753,
            "precision_weighted": 0.497753,
            "recall": 0.49776,
            "recall_weighted": 0.49776,
            "ap": 0.498885,
            "ap_weighted": 0.498885
          },
          {
            "accuracy": 0.50252,
            "f1": 0.499772,
            "f1_weighted": 0.499772,
            "precision": 0.502577,
            "precision_weighted": 0.502577,
            "recall": 0.50252,
            "recall_weighted": 0.50252,
            "ap": 0.501266,
            "ap_weighted": 0.501266
          },
          {
            "accuracy": 0.51228,
            "f1": 0.500223,
            "f1_weighted": 0.500223,
            "precision": 0.513592,
            "precision_weighted": 0.513592,
            "recall": 0.51228,
            "recall_weighted": 0.51228,
            "ap": 0.506359,
            "ap_weighted": 0.506359
          },
          {
            "accuracy": 0.51148,
            "f1": 0.510178,
            "f1_weighted": 0.510178,
            "precision": 0.511603,
            "precision_weighted": 0.511603,
            "recall": 0.51148,
            "recall_weighted": 0.51148,
            "ap": 0.505887,
            "ap_weighted": 0.505887
          },
          {
            "accuracy": 0.50612,
            "f1": 0.505747,
            "f1_weighted": 0.505747,
            "precision": 0.506139,
            "precision_weighted": 0.506139,
            "recall": 0.50612,
            "recall_weighted": 0.50612,
            "ap": 0.5031,
            "ap_weighted": 0.5031
          }
        ],
        "accuracy": 0.503196,
        "f1": 0.501408,
        "f1_weighted": 0.501408,
        "precision": 0.503349,
        "precision_weighted": 0.503349,
        "recall": 0.503196,
        "recall_weighted": 0.503196,
        "ap": 0.501662,
        "ap_weighted": 0.501662,
        "main_score": 0.503196,
        "hf_subset": "default",
        "languages": [
          "eng-Latn"
        ]
      }
    ]
  },
  "evaluation_time": 131.1623411178589,
  "kg_co2_emissions": null,
  "date": null
}